text_to_curses/__init__.py
text_to_curses/cli.py
text_to_curses/renderer.py
text_to_curses/utils.py
text_to_curses-0.1.0.dist-info/licenses/LICENSE
text_to_curses-0.1.0.dist-info/METADATA
text_to_curses-0.1.0.dist-info/WHEEL
text_to_curses-0.1.0.dist-info/entry_points.txt
text_to_curses-0.1.0.dist-info/top_level.txt
text_to_curses-0.1.0.dist-info/RECORD
