Metadata-Version: 2.4
Name: text-to-curses
Version: 0.1.0
Summary: A library for displaying documents in terminal with colors using curses
Home-page: https://github.com/da4games/Text-to-Curses
Author: da4games
License: MIT
Project-URL: Homepage, https://github.com/da4games/
Project-URL: Repository, https://github.com/da4games/Text-to-Curses
Project-URL: Issues, https://github.com/da4games/Text-to-Curses/issues
Classifier: Development Status :: 4 - Beta
Classifier: Intended Audience :: Developers
Classifier: License :: OSI Approved :: MIT License
Classifier: Operating System :: OS Independent
Classifier: Programming Language :: Python :: 3
Classifier: Programming Language :: Python :: 3.8
Classifier: Programming Language :: Python :: 3.9
Classifier: Programming Language :: Python :: 3.10
Classifier: Programming Language :: Python :: 3.11
Classifier: Programming Language :: Python :: 3.12
Classifier: Topic :: Text Processing
Classifier: Topic :: Terminals
Requires-Python: >=3.8
License-File: LICENSE
Requires-Dist: PyMuPDF>=1.20.0
Requires-Dist: python-docx>=0.8.11
Requires-Dist: beautifulsoup4>=4.11.0
Requires-Dist: webcolors>=1.12.0
Provides-Extra: dev
Requires-Dist: pytest>=7.0.0; extra == "dev"
Requires-Dist: black>=22.0.0; extra == "dev"
Requires-Dist: flake8>=4.0.0; extra == "dev"
Dynamic: home-page
Dynamic: license-file
Dynamic: requires-python
